si_units-0.11.0.dist-info/METADATA
si_units-0.11.0.dist-info/WHEEL
si_units/py.typed
si_units/_core.pyi
si_units/__init__.py
si_units/_core.pyd
si_units-0.11.0.dist-info/RECORD
