Metadata-Version: 2.4
Name: si-units
Version: 0.11.0
Summary: Representation of quantites, i.e. of unit valued scalars and arrays.
Keywords: physics,units,SI
Home-Page: https://github.com/itt-ustutt/quantity/tree/master/si-units
Author: Philipp Rehner <prehner@ethz.ch>, Gernot Bauer <bauer@itt.uni-stuttgart.de>
Author-email: Philipp Rehner <prehner@ethz.ch>, Gernot Bauer <bauer@itt.uni-stuttgart.de>
License: MIT OR Apache-2.0
Requires-Python: >=3.9
Project-URL: Source Code, https://github.com/itt-ustutt/quantity
